IUCN_API/IUCN_API.py
IUCN_API/__init__.py
IUCN_API/modules/Citations.py
IUCN_API/modules/Conservation.py
IUCN_API/modules/General.py
IUCN_API/modules/Groups.py
IUCN_API/modules/GrowthForm.py
IUCN_API/modules/Habitats.py
IUCN_API/modules/History.py
IUCN_API/modules/Narratives.py
IUCN_API/modules/Occurrence.py
IUCN_API/modules/Threats.py
IUCN_API/modules/View.py
IUCN_API/modules/Weblinks.py
IUCN_API/modules/__init__.py
IUCN_API/modules/Exceptions/APIKeyException.py
IUCN_API/modules/Exceptions/__init__.py
tests/__init__.py
tests/test_api_client.py
IUCN_API-0.1.6.dist-info/LICENSE
IUCN_API-0.1.6.dist-info/METADATA
IUCN_API-0.1.6.dist-info/WHEEL
IUCN_API-0.1.6.dist-info/top_level.txt
IUCN_API-0.1.6.dist-info/RECORD
